SMRCBuilder/Comms.py
SMRCBuilder/Exceptions.py
SMRCBuilder/Input.py
SMRCBuilder/Linker.py
SMRCBuilder/Logs.py
SMRCBuilder/Update.py
SMRCBuilder/__init__.py
SMRCBuilder-0.2.dist-info/LICENSE
SMRCBuilder-0.2.dist-info/METADATA
SMRCBuilder-0.2.dist-info/WHEEL
SMRCBuilder-0.2.dist-info/top_level.txt
SMRCBuilder-0.2.dist-info/RECORD
