Metadata-Version: 2.1
Name: SMRCBuilder
Version: 0.2
Summary: A Library To Help Build Your SmartRC Interface
Home-page: https://nokodaaddictions.github.io/Projects/SmartRC/SMRCBuilder.html
Author: NoKodaAddictions
Author-email: nokodaaddictions@gmail.com
License: MIT
Platform: UNKNOWN
Requires-Dist: pynput
